sayer/__init__.py
sayer/__main__.py
sayer/__version__.py
sayer/app.py
sayer/decorators.py
sayer/encoders.py
sayer/logging.py
sayer/middleware.py
sayer/params.py
sayer/py.typed
sayer/state.py
sayer/testing.py
sayer/cli/__init__.py
sayer/cli/docs.py
sayer/cli/new.py
sayer/conf/__init__.py
sayer/conf/global_settings.py
sayer/core/__init__.py
sayer/core/client.py
sayer/core/engine.py
sayer/core/handlers.py
sayer/core/logging.py
sayer/core/plugins.py
sayer/core/utils.py
sayer/core/commands/__init__.py
sayer/core/commands/base.py
sayer/core/commands/config.py
sayer/core/commands/sayer.py
sayer/core/console/__init__.py
sayer/core/console/loader.py
sayer/core/console/sayer.py
sayer/core/groups/__init__.py
sayer/core/groups/base.py
sayer/core/groups/sayer.py
sayer/protocols/__init__.py
sayer/protocols/logging.py
sayer/utils/__init__.py
sayer/utils/coersion.py
sayer/utils/config.py
sayer/utils/console.py
sayer/utils/loader.py
sayer/utils/signature.py
sayer/utils/sync.py
sayer/utils/ui.py
sayer/utils/ui_helpers.py
sayer-0.7.6.dist-info/METADATA
sayer-0.7.6.dist-info/WHEEL
sayer-0.7.6.dist-info/entry_points.txt
sayer-0.7.6.dist-info/licenses/LICENSE
sayer-0.7.6.dist-info/RECORD
