Metadata-Version: 2.4
Name: sayer
Version: 0.7.6
Summary: The click running on steroids
Project-URL: Homepage, https://github.com/dymmond/sayer
Project-URL: Documentation, https://sayer.dymmond.com
Project-URL: Changelog, https://sayer.dymmond.com/release-notes/
Project-URL: Funding, https://github.com/sponsors/tarsil
Project-URL: Source, https://github.com/dymmond/sayer
Author-email: Tiago Silva <tiago@tarsild.io>
License-Expression: MIT
License-File: LICENSE
Keywords: attrs,cli,click,command-line,dataclass,json,msgspec,pydantic,rich,sayer,serialization
Classifier: Development Status :: 4 - Beta
Classifier: Environment :: Web Environment
Classifier: Framework :: AnyIO
Classifier: Framework :: AsyncIO
Classifier: Intended Audience :: Developers
Classifier: Intended Audience :: Information Technology
Classifier: Intended Audience :: System Administrators
Classifier: License :: OSI Approved :: MIT License
Classifier: Operating System :: OS Independent
Classifier: Programming Language :: Python
Classifier: Programming Language :: Python :: 3
Classifier: Programming Language :: Python :: 3 :: Only
Classifier: Programming Language :: Python :: 3.10
Classifier: Programming Language :: Python :: 3.11
Classifier: Programming Language :: Python :: 3.12
Classifier: Programming Language :: Python :: 3.13
Classifier: Programming Language :: Python :: 3.14
Classifier: Topic :: Internet
Classifier: Topic :: Internet :: WWW/HTTP
Classifier: Topic :: Internet :: WWW/HTTP :: HTTP Servers
Classifier: Topic :: Software Development
Classifier: Topic :: Software Development :: Libraries
Classifier: Topic :: Software Development :: Libraries :: Application Frameworks
Classifier: Topic :: Software Development :: Libraries :: Python Modules
Classifier: Typing :: Typed
Requires-Python: >=3.10
Requires-Dist: anyio>=4.9.0
Requires-Dist: click<9.0.0,>=8.3.1
Requires-Dist: monkay>=0.4.2
Requires-Dist: rich>=14.0.0
Requires-Dist: typing-extensions>=4.13.2
Provides-Extra: testing
Requires-Dist: anyio[trio]<6.0.0,>=4.9.0; extra == 'testing'
Requires-Dist: attrs; extra == 'testing'
Requires-Dist: autoflake<3.0.0,>=2.0.2; extra == 'testing'
Requires-Dist: black<25.0,==24.1.1; extra == 'testing'
Requires-Dist: ipdb; extra == 'testing'
Requires-Dist: isort<6.0.0,>=5.12.0; extra == 'testing'
Requires-Dist: msgspec; extra == 'testing'
Requires-Dist: pydantic; extra == 'testing'
Requires-Dist: pytest-asyncio>=0.26.0; extra == 'testing'
Requires-Dist: pytest-cov<5.0.0,>=4.0.0; extra == 'testing'
Requires-Dist: pytest<9.0.0,>=7.2.2; extra == 'testing'
